fang/__init__.py
fang/calc.py
fang_module-0.0.1.dist-info/METADATA
fang_module-0.0.1.dist-info/WHEEL
fang_module-0.0.1.dist-info/top_level.txt
fang_module-0.0.1.dist-info/RECORD
